odoo/addons/purchase_incoming_product/README.rst
odoo/addons/purchase_incoming_product/__init__.py
odoo/addons/purchase_incoming_product/__manifest__.py
odoo/addons/purchase_incoming_product/i18n/it.po
odoo/addons/purchase_incoming_product/i18n/purchase_incoming_product.pot
odoo/addons/purchase_incoming_product/i18n/purchase_incoming_products.pot
odoo/addons/purchase_incoming_product/readme/CONTRIBUTORS.rst
odoo/addons/purchase_incoming_product/readme/DESCRIPTION.rst
odoo/addons/purchase_incoming_product/readme/USAGE.rst
odoo/addons/purchase_incoming_product/static/description/icon.png
odoo/addons/purchase_incoming_product/static/description/index.html
odoo/addons/purchase_incoming_product/views/purchase_incoming_products.xml
odoo14_addon_purchase_incoming_product-14.0.1.0.1.dev4.dist-info/METADATA
odoo14_addon_purchase_incoming_product-14.0.1.0.1.dev4.dist-info/WHEEL
odoo14_addon_purchase_incoming_product-14.0.1.0.1.dev4.dist-info/top_level.txt
odoo14_addon_purchase_incoming_product-14.0.1.0.1.dev4.dist-info/RECORD
