Metadata-Version: 2.1
Name: odoo14-addon-purchase_incoming_product
Version: 14.0.1.0.1.dev4
Summary: Module that generates a view for incoming products
Home-page: https://github.com/OCA/purchase-reporting
Author: Jarsa Sistemas,Odoo SA,Odoo Community Association (OCA)
Author-email: support@odoo-community.org
License: LGPL-3
Classifier: Programming Language :: Python
Classifier: Framework :: Odoo
Classifier: Framework :: Odoo :: 14.0
Classifier: License :: OSI Approved :: GNU Lesser General Public License v3 (LGPLv3)
Requires-Python: >=3.6
Requires-Dist: odoo<14.1dev,>=14.0a
